{
  "port": "KdeSoftwares-Main",
  "name": "Breeze",
  "version": "6.2.2",
  "architectures": ["x86_64"],
  "description": "Artwork, styles and assets for the Breeze visual style for the Plasma Desktop",
  "website": "https://invent.kde.org/plasma/breeze",
  "installedFiles": [],
  "dependencies": [
    {
      "port": "ProgrammingTools-Main",
      "name": "Extra-Cmake-Modules",
      "version": ">=6.7.0",
      "options": []
    }
  ],
  "kernelDependencies": [],
  "options": [],
  "uniqueDependencies": [],
  "uniqueOptions": [],
  "selectedDependencies": [],
  "allowCodependencies": []
}
